jlrpy.py
jlrpy-1.7.1.dist-info/LICENSE
jlrpy-1.7.1.dist-info/METADATA
jlrpy-1.7.1.dist-info/WHEEL
jlrpy-1.7.1.dist-info/top_level.txt
jlrpy-1.7.1.dist-info/RECORD
