Metadata-Version: 2.1
Name: jlrpy
Version: 1.7.1
Summary: Control your Jaguar I-Pace
Home-page: https://github.com/ardevd/jlrpy
Author: ardevd
Author-email: 5gk633atf@relay.firefox.com
Classifier: Programming Language :: Python :: 3
Classifier: License :: OSI Approved :: MIT License
Classifier: Operating System :: OS Independent
Classifier: Intended Audience :: Developers
Classifier: Development Status :: 5 - Production/Stable
License-File: LICENSE
Requires-Dist: requests (>=2.26.0)
